email_scraper/__init__.py
email_scraper/cli.py
email_scraper/formatters/__init__.py
email_scraper/formatters/json.py
email_scraper/processors/__init__.py
email_scraper/processors/example.py
swecc_email_scraper-0.1.2.dist-info/METADATA
swecc_email_scraper-0.1.2.dist-info/WHEEL
swecc_email_scraper-0.1.2.dist-info/entry_points.txt
swecc_email_scraper-0.1.2.dist-info/licenses/LICENSE
swecc_email_scraper-0.1.2.dist-info/RECORD
