Metadata-Version: 2.4
Name: swecc-email-scraper
Version: 0.1.2
Summary: A Python CLI tool for analyzing email data in mbox format
Project-URL: Homepage, https://github.com/swecc/email-scraper
Project-URL: Documentation, https://github.com/swecc/email-scraper#readme
Project-URL: Issues, https://github.com/swecc/email-scraper/issues
Author-email: SWECC Labs <swecc@uw.edu>
License-Expression: MIT
License-File: LICENSE
Keywords: analysis,cli,email,mbox
Classifier: Development Status :: 3 - Alpha
Classifier: Intended Audience :: Developers
Classifier: License :: OSI Approved :: MIT License
Classifier: Programming Language :: Python :: 3
Classifier: Programming Language :: Python :: 3.10
Classifier: Programming Language :: Python :: 3.11
Classifier: Programming Language :: Python :: 3.12
Requires-Python: >=3.10
Requires-Dist: click
Requires-Dist: rich
Provides-Extra: dev
Requires-Dist: black; extra == 'dev'
Requires-Dist: build; extra == 'dev'
Requires-Dist: mkdocs; extra == 'dev'
Requires-Dist: mkdocs-material; extra == 'dev'
Requires-Dist: mkdocstrings[python]; extra == 'dev'
Requires-Dist: mypy; extra == 'dev'
Requires-Dist: pre-commit; extra == 'dev'
Requires-Dist: pytest; extra == 'dev'
Requires-Dist: pytest-asyncio; extra == 'dev'
Requires-Dist: ruff; extra == 'dev'
Requires-Dist: twine; extra == 'dev'
Requires-Dist: types-click; extra == 'dev'
Requires-Dist: types-markdown; extra == 'dev'
Requires-Dist: types-pyyaml; extra == 'dev'
Requires-Dist: types-requests; extra == 'dev'
Provides-Extra: docs
Requires-Dist: mkdocs; extra == 'docs'
Requires-Dist: mkdocs-material; extra == 'docs'
Requires-Dist: mkdocstrings[python]; extra == 'docs'
Provides-Extra: lint
Requires-Dist: black; extra == 'lint'
Requires-Dist: mypy; extra == 'lint'
Requires-Dist: pre-commit; extra == 'lint'
Requires-Dist: ruff; extra == 'lint'
Requires-Dist: types-click; extra == 'lint'
Requires-Dist: types-markdown; extra == 'lint'
Requires-Dist: types-pyyaml; extra == 'lint'
Requires-Dist: types-requests; extra == 'lint'
Provides-Extra: test
Requires-Dist: pytest; extra == 'test'
Requires-Dist: pytest-asyncio; extra == 'test'
